oxonfair/__init__.py
oxonfair/version.py
oxonfair/learners/__init__.py
oxonfair/learners/efficient_compute.py
oxonfair/learners/fair.py
oxonfair/learners/fair_frontier.py
oxonfair/utils/__init__.py
oxonfair/utils/conditional_group_metrics.py
oxonfair/utils/dataset_loader.py
oxonfair/utils/group_metric_classes.py
oxonfair/utils/group_metrics.py
oxonfair/utils/performance.py
oxonfair/utils/scipy_metrics_cont_wrapper.py
oxonfair-0.2.1.11.dist-info/LICENSE
oxonfair-0.2.1.11.dist-info/METADATA
oxonfair-0.2.1.11.dist-info/WHEEL
oxonfair-0.2.1.11.dist-info/namespace_packages.txt
oxonfair-0.2.1.11.dist-info/top_level.txt
oxonfair-0.2.1.11.dist-info/zip-safe
oxonfair-0.2.1.11.dist-info/RECORD
