Metadata-Version: 2.1
Name: oxonfair
Version: 0.2.1.11
Summary: Toolkit for evaluating and enforcing ML model fairness
Home-page: https://github.com/oxfordinternetinstitute/oxonfair
Author: Governance of Emerging Technologies Programme (Oxford Internet Insitute)
License: Apache-2.0
Project-URL: Homepage, https://github.com/ChrisMRuss/oxon-fair/
Project-URL: Issues, https://github.com/ChrisMRuss/oxon-fair/issues
Classifier: Development Status :: 4 - Beta
Classifier: Intended Audience :: Education
Classifier: Intended Audience :: Developers
Classifier: Intended Audience :: Science/Research
Classifier: Intended Audience :: Customer Service
Classifier: Intended Audience :: Financial and Insurance Industry
Classifier: Intended Audience :: Healthcare Industry
Classifier: Intended Audience :: Telecommunications Industry
Classifier: Operating System :: MacOS
Classifier: Operating System :: Microsoft :: Windows
Classifier: Operating System :: POSIX
Classifier: Operating System :: Unix
Classifier: Programming Language :: Python :: 3
Classifier: Programming Language :: Python :: 3.8
Classifier: Programming Language :: Python :: 3.9
Classifier: Programming Language :: Python :: 3.10
Classifier: Programming Language :: Python :: 3.11
Classifier: Topic :: Software Development
Classifier: Topic :: Scientific/Engineering :: Artificial Intelligence
Classifier: Topic :: Scientific/Engineering :: Information Analysis
Classifier: Topic :: Scientific/Engineering :: Image Recognition
Requires-Python: >=3.8
License-File: LICENSE
Requires-Dist: numpy >=1.21.4
Requires-Dist: pandas >=1.2.5
Requires-Dist: scikit-learn
Requires-Dist: ucimlrepo
Provides-Extra: full
Requires-Dist: autogluon.tabular ; extra == 'full'
Requires-Dist: matplotlib ; extra == 'full'
Requires-Dist: torch ; extra == 'full'
Requires-Dist: jupyterlab ; extra == 'full'
Requires-Dist: xgboost ; extra == 'full'
Provides-Extra: notebooks
Requires-Dist: autogluon.tabular ; extra == 'notebooks'
Requires-Dist: matplotlib ; extra == 'notebooks'
Requires-Dist: torch ; extra == 'notebooks'
Requires-Dist: fairlearn ; extra == 'notebooks'
Requires-Dist: jupyterlab ; extra == 'notebooks'
Requires-Dist: fairret ; extra == 'notebooks'
Requires-Dist: xgboost ; extra == 'notebooks'
Provides-Extra: tests
Requires-Dist: autogluon.tabular ; extra == 'tests'
Requires-Dist: matplotlib ; extra == 'tests'
Requires-Dist: torch ; extra == 'tests'
Requires-Dist: pytest ; extra == 'tests'
Requires-Dist: fairlearn ; extra == 'tests'
Requires-Dist: pytest-cov ; extra == 'tests'
Requires-Dist: linkcheckmd ; extra == 'tests'
Requires-Dist: jupyterlab ; extra == 'tests'
Requires-Dist: tabulate ; extra == 'tests'
Requires-Dist: tox ; extra == 'tests'
Requires-Dist: flake8 ; extra == 'tests'
Requires-Dist: ipynbcompress ; extra == 'tests'
Requires-Dist: nbmake ; extra == 'tests'
Requires-Dist: fairret ; extra == 'tests'
Requires-Dist: xgboost ; extra == 'tests'
